Workbook

Sheet Cabecera-Cpte
A1: Datos Cabecera Comprobante
A2: Comprobante | D2: Datos Particulares | O2: Beneficiario | Q2: Comprobante origen unico | U2: Identificador del Trámite | X2: Moneda de la Operación | AB2: Tipo Medio de Pago | AC2: Documento Respaldatorio | AF2: Grupo:Fechas | AI2: Importe | AJ2: Observaciones
D3: Clase Factura | E3: Identificación | H3: Fecha | I3: Periodo Facturado | K3: Código de Autorización | N3: Incluye Sueldos | O3: Identificación
A4: Nro Etd Emisora | B4: Tipo | C4: Ejercicio | E4: Letra | F4: Sucursal | G4: Número | H4: Próx.Vto. | I4: Desde | J4: Hasta | K4: Tipo | L4: Número | M4: F.Vto. | O4: Tipo | P4: Numero | Q4: Nro Etd. Emisora | R4: Tipo | S4: Ejercicio | T4: Número | U4: Tipo | V4: Identificación | W4: Año | X4: Moneda | Y4: Tipo de Cotización | Z4: Fecha | AA4: Cotización | AC4: Tipo | AD4: Número | AE4: Ejercicio | AF4: Comprobante | AG4: Vencimiento | AH4: P.Impacto | AI4: Total MO | AK4: COD | AL4: UG | AM4: #
A5: 326 | B5: FACGS | C5: 2026 | D5: FSB | E5: A | F5: 0501 | G5: 03320583 | K5: CESP | L5: 36502006083461 | M5: 21/12/2025 | O5: CUI | P5: 30655116512 | X5: ARP | AA5: 1 | AB5: RC | AF5: 15/12/2025 | AG5: 18/12/2025 | AI5: 56758.27 | AJ5: SERVICIO DE ELECTRICIDAD CORRESPONDIENTE A EDESUR, Cliente: 02001253 - Factura N°: 03320583 - Importe: $ 56758,27 | AM5: =LEN(AJ5)
A6: 326 | B6: FACGS | C6: 2026 | D6: FSB | E6: B | F6: 0501 | G6: 68160280 | K6: CESP | L6: 36502006083461 | M6: 21/12/2025 | O6: CUI | P6: 30655116512 | X6: ARP | AA6: 1 | AB6: RC | AF6: 15/12/2025 | AG6: 18/12/2025 | AI6: 268877.92 | AJ6: SERVICIO DE ELECTRICIDAD CORRESPONDIENTE A EDESUR, Cliente: 02000183 - Factura N°: 68160280 - Importe: $ 268877,92
A7: 326 | B7: FACGS | C7: 2026 | D7: FSB | E7: B | F7: 0501 | G7: 67732551 | K7: CESP | L7: 36492006072441 | M7: 14/12/2025 | O7: CUI | P7: 30655116512 | X7: ARP | AA7: 1 | AB7: RC | AF7: 11/12/2025 | AG7: 14/12/2025 | AI7: 88386.89 | AJ7: SERVICIO DE ELECTRICIDAD CORRESPONDIENTE A EDESUR, Cliente: 02000408 - Factura N°: 67732551 - Importe: $ 88386,89
A8: 326 | B8: FACGS | C8: 2026 | D8: FSB | E8: B | F8: 0501 | G8: 68431810 | K8: CESP | L8: 36502006083461 | M8: 21/12/2025 | O8: CUI | P8: 30655116512 | X8: ARP | AA8: 1 | AB8: RC | AF8: 16/12/2025 | AG8: 19/12/2025 | AI8: 1103272.4 | AJ8: SERVICIO DE ELECTRICIDAD CORRESPONDIENTE A EDESUR, Cliente: 02001460 - Factura N°: 68431810 - Importe: $ 1103272,44
A9: 326 | B9: FACGS | C9: 2026 | D9: FSB | E9: B | F9: 0501 | G9: 66231308 | K9: CESP | L9: 36472006050285 | M9: 30/11/2025 | O9: CUI | P9: 30655116512 | X9: ARP | AA9: 1 | AB9: RC | AF9: 28/11/2025 | AG9: 01/12/2025 | AI9: 663886.85 | AJ9: SERVICIO DE ELECTRICIDAD CORRESPONDIENTE A EDESUR, Cliente: 02001606 - Factura N°: 66231308 - Importe: $ 663886,85
A10: 326 | B10: FACGS | C10: 2026 | D10: FSB | E10: B | F10: 0501 | G10: 68610151 | K10: CESP | L10: 36502006083461 | M10: 21/12/2025 | O10: CUI | P10: 30655116512 | X10: ARP | AA10: 1 | AB10: RC | AF10: 17/12/2025 | AG10: 20/12/2025 | AI10: 346414.56 | AJ10: SERVICIO DE ELECTRICIDAD CORRESPONDIENTE A EDESUR, Cliente: 02001860 - Factura N°: 68610151 - Importe: $ 346414,56
A11: 326 | B11: FACGS | C11: 2026 | D11: FSB | E11: B | F11: 0501 | G11: 66231310 | K11: CESP | L11: 36472006050285 | M11: 30/11/2025 | O11: CUI | P11: 30655116512 | X11: ARP | AA11: 1 | AB11: RC | AF11: 28/11/2025 | AG11: 01/12/2025 | AI11: 164997.75 | AJ11: SERVICIO DE ELECTRICIDAD CORRESPONDIENTE A EDESUR, Cliente: 02002911 - Factura N°: 66231310 - Importe: $ 164997,75
A12: 326 | B12: FACGS | C12: 2026 | D12: FSB | E12: B | F12: 0501 | G12: 68179945 | K12: CESP | L12: 36502006083461 | M12: 21/12/2025 | O12: CUI | P12: 30655116512 | X12: ARP | AA12: 1 | AB12: RC | AF12: 15/12/2025 | AG12: 18/12/2025 | AI12: 21904.18 | AJ12: SERVICIO DE ELECTRICIDAD CORRESPONDIENTE A EDESUR, Cliente: 02003808 - Factura N°: 68179945 - Importe: $ 21904,18
A13: 326 | B13: FACGS | C13: 2026 | D13: FSB | E13: B | F13: 0501 | G13: 67565199 | K13: CESP | L13: 36492006072441 | M13: 14/12/2025 | O13: CUI | P13: 30655116512 | X13: ARP | AA13: 1 | AB13: RC | AF13: 10/12/2025 | AG13: 13/12/2025 | AI13: 274713.96 | AJ13: SERVICIO DE ELECTRICIDAD CORRESPONDIENTE A EDESUR, Cliente: 03394120 - Factura N°: 67565199 - Importe: $ 274713,96
A14: 326 | B14: FACGS | C14: 2026 | D14: FSB | E14: B | F14: 0501 | G14: 68750387 | K14: CESP | L14: 36502006083461 | M14: 21/12/2025 | O14: CUI | P14: 30655116512 | X14: ARP | AA14: 1 | AB14: RC | AF14: 18/12/2025 | AG14: 21/12/2025 | AI14: 471137.91 | AJ14: SERVICIO DE ELECTRICIDAD CORRESPONDIENTE A EDESUR, Cliente: 03430416 - Factura N°: 68750387 - Importe: $ 471137,91
A15: 326 | B15: FACGS | C15: 2026 | D15: FSB | E15: B | F15: 0501 | G15: 68613692 | K15: CESP | L15: 36502006083461 | M15: 21/12/2025 | O15: CUI | P15: 30655116512 | X15: ARP | AA15: 1 | AB15: RC | AF15: 17/12/2025 | AG15: 20/12/2025 | AI15: 1252987.4 | AJ15: SERVICIO DE ELECTRICIDAD CORRESPONDIENTE A EDESUR, Cliente: 03650412 - Factura N°: 68613692 - Importe: $ 1252987,35
A16: 326 | B16: FACGS | C16: 2026 | D16: FSB | E16: B | F16: 0501 | G16: 66568858 | K16: CESP | L16: 36482006060383 | M16: 07/12/2025 | O16: CUI | P16: 30655116512 | X16: ARP | AA16: 1 | AB16: RC | AF16: 02/12/2025 | AG16: 05/12/2025 | AI16: 615634.18 | AJ16: SERVICIO DE ELECTRICIDAD CORRESPONDIENTE A EDESUR, Cliente: 03650412 - Factura N°: 66568858 - Importe: $ 615634,18
A17: 326 | B17: FACGS | C17: 2026 | D17: FSB | E17: B | F17: 0501 | G17: 66783232 | K17: CESP | L17: 36482006060383 | M17: 07/12/2025 | O17: CUI | P17: 30655116512 | X17: ARP | AA17: 1 | AB17: RC | AF17: 03/12/2025 | AG17: 06/12/2025 | AI17: 759911.06 | AJ17: SERVICIO DE ELECTRICIDAD CORRESPONDIENTE A EDESUR, Cliente: 03826061 - Factura N°: 66783232 - Importe: $ 759911,06
... A66: 326 | B66: FACGS | C66: 2026 | D66: FSB | E66: B | F66: 9905 | G66: 01975093 | K66: CESP | L66: 36512006091389 | M66: 31/12/2025 | O66: CUI | P66: 30655116512 | X66: ARP | AA66: 1 | AB66: RC | AF66: 23/12/2025 | AG66: 26/12/2025 | AI66: 440220 | AJ66: SERVICIO DE ELECTRICIDAD CORRESPONDIENTE A EDESUR, Cliente: 80514869 - Factura N°: 01975093 - Importe: $ 440220,00

Sheet Pronto Pago
A1: Identificación Cabecera Cpte GS | H1: Pronto Pago
A2: Identificación | D2: Beneficiario | F2: Código de Autorización | H2: Fecha Descuento | I2: % Descuento | J2: Observaciones
A3: Letra | B3: Sucursal | C3: Número | D3: Tipo | E3: Numero | F3: Tipo | G3: Número

Sheet Detalle Cpte FacGS
A1: Identificación Cabecera Cpte GS
A2: Identificación | D2: Beneficiario | F2: Código de Autorización | H2: Código Catálogo | I2: Descripción | J2: Objeto del Gasto | N2: Cantidad | O2: Unidad Medida | P2: Moneda Origen
A3: Letra | B3: Sucursal | C3: Número | D3: Tipo | E3: Numero | F3: Tipo | G3: Número | J3: Inciso | K3: Partida Principal | L3: Partida Parcial | M3: Partida SubParcial | P3: Precio Unitario | Q3: %IVA | R3: Imp.OtrosCptos
A4: ='Cabecera-Cpte'!E5 | B4: ='Cabecera-Cpte'!F5 | C4: ='Cabecera-Cpte'!G5 | D4: ='Cabecera-Cpte'!O5 | E4: ='Cabecera-Cpte'!P5 | F4: ='Cabecera-Cpte'!K5 | G4: ='Cabecera-Cpte'!L5 | H4: 3.1.1-2390-1 | J4: 3 | K4: 1 | L4: 1 | M4: 0 | N4: 1 | P4: ='Cabecera-Cpte'!AI5

Sheet Detalle Presupuestario  FACGS
A1: Identificación Cabecera Cpte GS | H1: Items Prespuestarios
A2: Identificación | D2: Beneficiario | F2: Código de Autorización | H2: Solicitud | I2: Cpte.Compromiso | J2: Institución | M2: SAF | N2: UD | O2: Apertura Programática | T2: UG | U2: Objeto del Gasto | Y2: Ffin | Z2: Moneda | AA2: Entidad Destino | AB2: PEX | AC2: BAPIN | AD2: SIGADE | AE2: Gan | AF2: IVA | AG2: SUSS | AH2: %IVA | AI2: Imp. Otros Conceptos MO | AJ2: Importe Factura MO
A3: Letra | B3: Sucursal | C3: Número | D3: Tipo | E3: Numero | F3: Tipo | G3: Número | J3: Jurisdicción | K3: SubJurisdicción | L3: Entidad | O3: Programa | P3: Subprograma | Q3: Proyecto | R3: Actividad | S3: Obra | U3: Inciso | V3: Partida Principal | W3: Partida Parcial | X3: Partida SubParcial
A4: ='Cabecera-Cpte'!E5 | B4: ='Cabecera-Cpte'!F5 | C4: ='Cabecera-Cpte'!G5 | D4: ='Cabecera-Cpte'!O5 | E4: ='Cabecera-Cpte'!P5 | F4: ='Cabecera-Cpte'!K5 | G4: ='Cabecera-Cpte'!L5 | J4: 41 | K4: 4 | L4: 0 | M4: ='Cabecera-Cpte'!A5 | N4: ='Cabecera-Cpte'!AK5 | O4: 1 | P4: 0 | Q4: 0 | R4: 1 | S4: 0 | T4: ='Cabecera-Cpte'!AL5 | U4: ='Detalle Cpte FacGS'!J4 | V4: ='Detalle Cpte FacGS'!K4 | W4: ='Detalle Cpte FacGS'!L4 | X4: ='Detalle Cpte FacGS'!M4 | Y4: 11 | Z4: 1 | AB4: 0 | AC4: 0 | AE4: EXE | AF4: EXE | AG4: EXE | AH4: 0 | AJ4: ='Cabecera-Cpte'!AI5

Sheet Deducciones
A1: Identificación Cabecera Cpte GS | H1: Deducciones
A2: Identificación | D2: Beneficiario | F2: Código de Autorización | H2: Código | I2: Cuenta Bancaria Beneficiario | J2: Importe Deducción MCL
A3: Letra | B3: Sucursal | C3: Número | D3: Tipo | E3: Numero | F3: Tipo | G3: Número

Sheet Det Deducc x Cptos
A1: Identificación Cabecera Cpte GS | H1: Código Deducción | I1: Detalle de Deducción por Conceptos
A2: Identificación | D2: Beneficiario | F2: Código de Autorización
A3: Letra | B3: Sucursal | C3: Número | D3: Tipo | E3: Numero | F3: Tipo | G3: Número | I3: C. Impositivo | J3: Imp Deducción MCL

Sheet Hoja4

Sheet BENEFICIARIOS
A1: Número | B1: Denominación | C1: CUI | D1: CUIT | E1: IVA | F1: GAN | G1: N/A Cod. Autorización
A2: 1688 | B2: ENTE PROVINCIAL DE AGUA Y SANEAMIENTO | C2: CUI | D2: 30999273498 | E2: RI | F2: EXE | G2: CESP
A3: 1691 | B3: D.P.O.S.S. DIRECCION PROVINCIAL DE OBRAS Y SERVICIOS SANITARIOS | C3: CUI | D3: 30587083074 | E3: RI | F3: NI | G3: CESP
A4: 3980 | B4: SERVICIO DE AGUA Y MANTENIMIENTO EMPRESA DEL ESTADO PROVINCIAL S A M E E P | C4: CUI | D4: 30556366906 | E4: RI | F4: RI | G4: NA
A5: 5102 | B5: OBRAS SANITARIAS SOCIEDAD DEL ESTADO SAN JUAN | C5: CUI | D5: 30999032849 | E5: RI | F5: NI | G5: NA
A6: 9930 | B6: AGUAS DE CORRIENTES S.A. | C6: CUI | D6: 30645168794 | E6: RI | F6: RI | G6: CESP
A7: 12112 | B7: COOPERATIVA DE AGUA POTABLE Y OTROS SERVICIOS PUB DE SAN MARTIN DE LOS ANDES | C7: CUI | D7: 30571865684 | E7: RI | F7: EXE | G7: CESP
A8: 12188 | B8: AGUAS DE FORMOSA SA. | C8: CUI | D8: 30671378047 | E8: RI | F8: RI | G8: CESP
A9: 12700 | B9: COOPERATIVA DE TRABAJO 15 DE MAYO LIMITADA | C9: CUI | D9: 30651082575 | E9: RI | F9: EXE | G9: CESP
A10: 13239 | B10: OBRAS SANITARIAS DE MAR DEL PLATA S.E. | C10: CUI | D10: 30630467620 | E10: NC | F10: EXE | G10: NA
A11: 24441 | B11: COOPERATIVA DE TRABAJO SUDESTE LTDA. | C11: CUI | D11: 30668249651 | E11: RI | F11: EXE | G11: CESP
A12: 48440 | B12: OBRAS SANITARIAS MUNICIPAL - ENTE DESCENTRALIZADO | C12: CUI | D12: 30642668281 | E12: NC | F12: EXE | G12: NA
A13: 69790 | B13: AGUAS CORDOBESAS S.A. | C13: CUI | D13: 33689822989 | E13: RI | F13: RI | G13: NA
A14: 92132 | B14: AGUAS DE SANTIAGO S.A. | C14: CUI | D14: 30686692899 | E14: RI | F14: RI | G14: CESP
A15: 125649 | B15: SERVICIOS DE AGUA DE MISIONES S A | C15: CUI | D15: 33698095909 | E15: RI | F15: RI | G15: CESP
A16: 153200 | B16: AGUAS RIONEGRINAS SOCIEDAD ANONIMA | C16: CUI | D16: 30707421041 | E16: RI | F16: RI | G16: NA
A17: 167215 | B17: AGUAS BONAERENSES S.A. | C17: CUI | D17: 30707919902 | E17: RI | F17: RI | G17: CESP
A18: 173985 | B18: ENTE AUTARQUICO MUNICIPAL DE SERVICIO PUBLICOS (EAMSEP) | C18: CUI | D18: 30672616774 | E18: RI | F18: EXE | G18: NA
A19: 196990 | B19: SOCIEDAD DE AGUAS DEL TUCUMAN - SAPEM | C19: CUI | D19: 30708617888 | E19: RI | F19: RI | G19: CESP
A20: 250244 | B20: AGUA Y SANEAMIENTOS ARGENTINOS S.A. | C20: CUI | D20: 30709565075 | E20: RI | F20: RI | G20: NA
A21: 250552 | B21: AGUAS SANTAFESINAS S.A. | C21: CUI | D21: 30709514144 | E21: RI | F21: RI | G21: NA
A22: 316725 | B22: AGUAS DE CATAMARCA S.A. CON PARTICIPACION ESTATAL MAYORITARIA S.A.P.E.M. | C22: CUI | D22: 30710500513 | E22: RI | F22: RI | G22: CESP
A23: 344829 | B23: COMPAÑIA SALTEÑA DE AGUA Y SANEAMIENTO S.A | C23: CUI | D23: 33710974549 | E23: RI | F23: RI | G23: CESP
A24: 374869 | B24: AGUAS RIOJANAS S.A.P.E.M. | C24: CUI | D24: 30711273197 | E24: RI | F24: RI | G24: CESP
A25: 384417 | B25: AGUA Y SANEAMIENTO MENDOZA S.A. | C25: CUI | D25: 30711513562 | E25: RI | F25: RI | G25: NA
A26: 490353 | B26: ENTE MUNICIPAL DE OBRAS Y SERVICIOS DE SANEAMIENTO E M O S S | C26: CUI | D26: 30668543339 | E26: EXE | F26: EXE | G26: NA
A27: 594725 | B27: AGUA POTABLE Y SANEAMIENTO DE JUJUY SOCIEDAD DEL ESTADO | C27: CUI | D27: 30715273906 | E27: RI | F27: RI | G27: CESP
