Workbook

Sheet Cabecera-Cpte
A1: Datos Cabecera Comprobante
A2: Comprobante | D2: Datos Particulares | O2: Beneficiario | Q2: Comprobante origen unico | U2: Identificador del Trámite | X2: Moneda de la Operación | AB2: Tipo Medio de Pago | AC2: Documento Respaldatorio | AF2: Grupo:Fechas | AI2: Importe | AJ2: Observaciones
D3: Clase Factura | E3: Identificación | H3: Fecha | I3: Periodo Facturado | K3: Código de Autorización | N3: Incluye Sueldos | O3: Identificación
A4: Nro Etd Emisora | B4: Tipo | C4: Ejercicio | E4: Letra | F4: Sucursal | G4: Número | H4: Próx.Vto. | I4: Desde | J4: Hasta | K4: Tipo | L4: Número | M4: F.Vto. | O4: Tipo | P4: Numero | Q4: Nro Etd. Emisora | R4: Tipo | S4: Ejercicio | T4: Número | U4: Tipo | V4: Identificación | W4: Año | X4: Moneda | Y4: Tipo de Cotización | Z4: Fecha | AA4: Cotización | AC4: Tipo | AD4: Número | AE4: Ejercicio | AF4: Comprobante | AG4: Vencimiento | AH4: P.Impacto | AI4: Total MO
A5: 326 | B5: FACGS | C5: =YEAR(TODAY()) -> 2026 | D5: FSB | E5: B | O5: CUI | X5: ARP | AA5: 1 | AB5: RC

Sheet Pronto Pago
A1: Identificación Cabecera Cpte GS | H1: Pronto Pago
A2: Identificación | D2: Beneficiario | F2: Código de Autorización | H2: Fecha Descuento | I2: % Descuento | J2: Observaciones
A3: Letra | B3: Sucursal | C3: Número | D3: Tipo | E3: Numero | F3: Tipo | G3: Número

Sheet Detalle Cpte FacGS
A1: Identificación Cabecera Cpte GS
A2: Identificación | D2: Beneficiario | F2: Código de Autorización | H2: Código Catálogo | I2: Descripción | J2: Objeto del Gasto | N2: Cantidad | O2: Unidad Medida | P2: Moneda Origen
A3: Letra | B3: Sucursal | C3: Número | D3: Tipo | E3: Numero | F3: Tipo | G3: Número | J3: Inciso | K3: Partida Principal | L3: Partida Parcial | M3: Partida SubParcial | P3: Precio Unitario | Q3: %IVA | R3: Imp.OtrosCptos
A4: ='Cabecera-Cpte'!E5 -> B | B4: ='Cabecera-Cpte'!F5 -> 0 | C4: ='Cabecera-Cpte'!G5 -> 0 | D4: ='Cabecera-Cpte'!O5 -> CUI | E4: ='Cabecera-Cpte'!P5 -> 0 | F4: ='Cabecera-Cpte'!K5 -> 0 | G4: ='Cabecera-Cpte'!L5 -> 0 | H4: 3.1.1-2390-1 | J4: 3 | K4: 1 | L4: 1 | M4: 0 | N4: 1 | P4: ='Cabecera-Cpte'!AI5 -> 0

Sheet Detalle Presupuestario  FACGS
A1: Identificación Cabecera Cpte GS | H1: Items Prespuestarios
A2: Identificación | D2: Beneficiario | F2: Código de Autorización | H2: Solicitud | I2: Cpte.Compromiso | J2: Institución | M2: SAF | N2: UD | O2: Apertura Programática | T2: UG | U2: Objeto del Gasto | Y2: Ffin | Z2: Moneda | AA2: Entidad Destino | AB2: PEX | AC2: BAPIN | AD2: SIGADE | AE2: Gan | AF2: IVA | AG2: SUSS | AH2: %IVA | AI2: Imp. Otros Conceptos MO | AJ2: Importe Factura MO
A3: Letra | B3: Sucursal | C3: Número | D3: Tipo | E3: Numero | F3: Tipo | G3: Número | J3: Jurisdicción | K3: SubJurisdicción | L3: Entidad | O3: Programa | P3: Subprograma | Q3: Proyecto | R3: Actividad | S3: Obra | U3: Inciso | V3: Partida Principal | W3: Partida Parcial | X3: Partida SubParcial
A4: ='Cabecera-Cpte'!E5 -> B | B4: ='Cabecera-Cpte'!F5 -> 0 | C4: ='Cabecera-Cpte'!G5 -> 0 | D4: ='Cabecera-Cpte'!O5 -> CUI | E4: ='Cabecera-Cpte'!P5 -> 0 | F4: ='Cabecera-Cpte'!K5 -> 0 | G4: ='Cabecera-Cpte'!L5 -> 0 | J4: 41 | K4: 4 | L4: 0 | M4: ='Cabecera-Cpte'!A5 -> 326 | O4: 1 | P4: 0 | Q4: 0 | R4: 1 | S4: 0 | U4: ='Detalle Cpte FacGS'!J4 -> 3 | V4: ='Detalle Cpte FacGS'!K4 -> 1 | W4: ='Detalle Cpte FacGS'!L4 -> 1 | X4: ='Detalle Cpte FacGS'!M4 -> 0 | Y4: 11 | Z4: 1 | AB4: 0 | AC4: 0 | AE4: EXE | AF4: EXE | AG4: EXE | AH4: 0 | AJ4: ='Cabecera-Cpte'!AI5 -> 0

Sheet Deducciones
A1: Identificación Cabecera Cpte GS | H1: Deducciones
A2: Identificación | D2: Beneficiario | F2: Código de Autorización | H2: Código | I2: Cuenta Bancaria Beneficiario | J2: Importe Deducción MCL
A3: Letra | B3: Sucursal | C3: Número | D3: Tipo | E3: Numero | F3: Tipo | G3: Número

Sheet Det Deducc x Cptos
A1: Identificación Cabecera Cpte GS | H1: Código Deducción | I1: Detalle de Deducción por Conceptos
A2: Identificación | D2: Beneficiario | F2: Código de Autorización
A3: Letra | B3: Sucursal | C3: Número | D3: Tipo | E3: Numero | F3: Tipo | G3: Número | I3: C. Impositivo | J3: Imp Deducción MCL
